MANIFEST.in
README.rst
setup.py
credo/__init__.py
credo/actions.py
credo/amazon.py
credo/asker.py
credo/compat.py
credo/crypto.py
credo/errors.py
credo/executor.py
credo/explorer.py
credo/helper.py
credo/overview.py
credo/pub_keys.py
credo/cred_types/__init__.py
credo/cred_types/amazon.py
credo/cred_types/environment.py
credo/cred_types/saml.py
credo/ext/manifest.json
credo/ext/src/bg/background.js
credo/ext/src/inject/inject.js
credo/server/__init__.py
credo/server/server.py
credo/structure/__init__.py
credo/structure/account.py
credo/structure/credential_path.py
credo/structure/credentials.py
credo/structure/keys.py
credo/structure/repository.py
credo/structure/user.py
credo/versioning/__init__.py
credo/versioning/base.py
credo/versioning/git.py
credo_manager.egg-info/PKG-INFO
credo_manager.egg-info/SOURCES.txt
credo_manager.egg-info/dependency_links.txt
credo_manager.egg-info/entry_points.txt
credo_manager.egg-info/requires.txt
credo_manager.egg-info/top_level.txt