Metadata-Version: 2.1
Name: credo-manager
Version: 0.5.2
Summary: Manager for aws credentials
Home-page: https://github.com/delfick/credo
Author: Stephen Moore
Author-email: stephen@delfick.com
License: MIT
Keywords: iam amazon credentials
Platform: UNKNOWN
Provides-Extra: git
Provides-Extra: tests
